[{"id": 0, "text": "CASH/CREDIT", "label": "others", "box": [238, 53, 334, 32], "linking": []}, {"id": 1, "text": "memo", "label": "others", "box": [241, 74, 334, 53], "linking": []}, {"id": 2, "text": "No", "label": "others", "box": [238, 95, 253, 86], "linking": []}, {"id": 3, "text": " Date.", "label": "others", "box": [239, 110, 264, 98], "linking": []}, {"id": 4, "text": "CASH/CREDIT", "label": "others", "box": [582, 46, 674, 26], "linking": []}, {"id": 5, "text": "memo", "label": "others", "box": [584, 67, 677, 46], "linking": []}, {"id": 6, "text": "No", "label": "others", "box": [585, 89, 599, 80], "linking": []}, {"id": 7, "text": "MRS. RISHORI R. NAGARKAR", "label": "w merchant name", "box": [62, 61, 207, 47], "linking": []}, {"id": 8, "text": "BCATERERS", "label": "w merchant name", "box": [102, 69, 168, 58], "linking": []}, {"id": 9, "text": "Deccan Gymkama, Ping 41100%", "label": "x merchant address beginning", "box": [64, 90, 205, 76], "linking": []}, {"id": 10, "text": " MRS.", "label": "w merchant name", "box": [391, 72, 416, 59], "linking": []}, {"id": 11, "text": " KISHORIR NAGARKAR", "label": "w merchant name", "box": [418, 71, 535, 55], "linking": []}, {"id": 12, "text": "CATERERS", "label": "w merchant name", "box": [434, 80, 490, 68], "linking": []}, {"id": 13, "text": " ghino", "label": "y merchant address inside", "box": [474, 99, 497, 86], "linking": [[13, 17]]}, {"id": 14, "text": " Ph - 25077033 95610953:", "label": "z merchant phone", "box": [75, 98, 187, 86], "linking": []}, {"id": 15, "text": " Deccan", "label": "y merchant address inside", "box": [391, 100, 423, 89], "linking": []}, {"id": 16, "text": " Gymilinha", "label": "y merchant address inside", "box": [425, 100, 472, 87], "linking": []}, {"id": 17, "text": " 411004", "label": "y merchant address inside", "box": [499, 98, 534, 84], "linking": [[13, 17]]}, {"id": 18, "text": " 4- le 19", "label": "bill date", "box": [266, 111, 313, 96], "linking": []}, {"id": 19, "text": " Ht", "label": "others", "box": [296, 136, 314, 120], "linking": []}, {"id": 20, "text": "Ph - 25877633.9661005307", "label": "z merchant phone", "box": [403, 110, 528, 94], "linking": []}, {"id": 21, "text": " American Express Services India", "label": "others", "box": [404, 136, 621, 113], "linking": []}, {"id": 22, "text": " M/L. American Express Services Tmin Put", "label": "others", "box": [32, 139, 291, 121], "linking": []}, {"id": 23, "text": " M ..", "label": "others", "box": [382, 137, 402, 122], "linking": []}, {"id": 24, "text": " Rit Lid", "label": "others", "box": [623, 128, 669, 111], "linking": []}, {"id": 25, "text": "Order No.", "label": "others", "box": [28, 172, 65, 161], "linking": []}, {"id": 26, "text": "Challan Ni", "label": "others", "box": [130, 170, 175, 160], "linking": []}, {"id": 27, "text": "Dole", "label": "others", "box": [235, 170, 257, 161], "linking": []}, {"id": 28, "text": "Order No", "label": "others", "box": [381, 170, 421, 161], "linking": []}, {"id": 29, "text": "Quantity", "label": "others", "box": [27, 194, 63, 184], "linking": []}, {"id": 30, "text": "Particulars", "label": "others", "box": [120, 193, 166, 183], "linking": []}, {"id": 31, "text": "Rate", "label": "others", "box": [229, 192, 248, 184], "linking": []}, {"id": 32, "text": "Amount", "label": "others", "box": [281, 188, 313, 180], "linking": []}, {"id": 33, "text": "Quantity", "label": "others", "box": [384, 193, 420, 183], "linking": []}, {"id": 34, "text": "Particulart", "label": "others", "box": [479, 190, 523, 180], "linking": []}, {"id": 35, "text": "Rute", "label": "others", "box": [586, 186, 606, 177], "linking": []}, {"id": 36, "text": "Amount", "label": "others", "box": [636, 181, 671, 171], "linking": []}, {"id": 37, "text": "10", "label": "e quantity", "box": [30, 224, 48, 210], "linking": []}, {"id": 38, "text": "Lunch", "label": "0 description beginning", "box": [90, 225, 134, 206], "linking": []}, {"id": 39, "text": "180", "label": "unit price", "box": [222, 224, 250, 210], "linking": []}, {"id": 40, "text": "10", "label": "e quantity", "box": [389, 223, 402, 211], "linking": []}, {"id": 41, "text": "Lunch", "label": "0 description beginning", "box": [434, 223, 479, 207], "linking": []}, {"id": 42, "text": "130", "label": "unit price", "box": [580, 216, 604, 204], "linking": []}, {"id": 43, "text": "12.00", "label": "5 total price per item", "box": [624, 216, 663, 202], "linking": []}, {"id": 44, "text": "1800 Ps", "label": "others", "box": [69, 371, 135, 349], "linking": []}, {"id": 45, "text": "Thank you", "label": "others", "box": [156, 465, 199, 454], "linking": []}, {"id": 46, "text": "Total", "label": "others", "box": [220, 465, 244, 455], "linking": []}, {"id": 47, "text": " 1800:", "label": "total amount", "box": [263, 468, 305, 448], "linking": []}, {"id": 48, "text": " 00", "label": "others", "box": [309, 467, 327, 448], "linking": []}, {"id": 49, "text": "Thank you", "label": "others", "box": [544, 458, 586, 447], "linking": []}, {"id": 50, "text": "Total", "label": "others", "box": [607, 456, 634, 446], "linking": []}, {"id": 51, "text": " 1800", "label": "total amount", "box": [643, 460, 683, 445], "linking": []}, {"id": 52, "text": " 00", "label": "others", "box": [696, 458, 715, 444], "linking": []}, {"id": 53, "text": "Goods once sold will not be taken back.", "label": "others", "box": [8, 488, 160, 475], "linking": []}, {"id": 54, "text": "ELOE", "label": "others", "box": [7, 501, 40, 491], "linking": []}, {"id": 55, "text": "Goods ance sold will not be taken back", "label": "others", "box": [395, 487, 547, 470], "linking": []}, {"id": 56, "text": " Propored by", "label": "others", "box": [168, 506, 220, 490], "linking": []}, {"id": 57, "text": " K. R AL", "label": "others", "box": [225, 505, 272, 486], "linking": []}, {"id": 58, "text": "Prepared by", "label": "others", "box": [559, 497, 607, 486], "linking": []}]